FastKmedoids/__init__.py
FastKmedoids/data.py
FastKmedoids/metrics.py
FastKmedoids/models.py
FastKmedoids/plots.py
fastkmedoids-0.0.48.dist-info/licenses/LICENSE
fastkmedoids-0.0.48.dist-info/METADATA
fastkmedoids-0.0.48.dist-info/WHEEL
fastkmedoids-0.0.48.dist-info/top_level.txt
fastkmedoids-0.0.48.dist-info/RECORD
