Metadata-Version: 2.4
Name: FastKmedoids
Version: 0.0.48
Summary: For more information, check out the official documentation of `FastKmedoids` at: https://fabioscielzoortiz.github.io/FastKmedoids-book/intro.html
Home-page: https://github.com/FabioScielzoOrtiz/FastKmedoids-package
Author: Fabio Scielzo Ortiz
Author-email: fabioscielzo98@gmail.com
Classifier: Programming Language :: Python :: 3
Classifier: License :: OSI Approved :: MIT License
Classifier: Operating System :: OS Independent
Requires-Python: >=3.7
License-File: LICENSE
Requires-Dist: polars
Requires-Dist: numpy
Dynamic: author
Dynamic: author-email
Dynamic: classifier
Dynamic: description
Dynamic: description-content-type
Dynamic: home-page
Dynamic: license-file
Dynamic: requires-dist
Dynamic: requires-python
Dynamic: summary
